libactor/__init__.py
libactor/actor/__init__.py
libactor/actor/_actor.py
libactor/actor/_state.py
libactor/actor/_version.py
libactor/cache/__init__.py
libactor/cache/backend.py
libactor/cache/backend_factory.py
libactor/cache/cache.py
libactor/cache/cache_args.py
libactor/cache/identitied_object.py
libactor/dag/__init__.py
libactor/dag/_dag.py
libactor/dag/_pipeline.py
libactor/executor/__init__.py
libactor/executor/ray.py
libactor/misc/__init__.py
libactor/misc/_fn_signature.py
libactor/misc/_misc.py
libactor/misc/_type_conversion.py
libactor/storage/__init__.py
libactor/storage/_global_storage.py
libactor/typing.py
libactor-2.6.3.dist-info/LICENSE
libactor-2.6.3.dist-info/METADATA
libactor-2.6.3.dist-info/WHEEL
libactor-2.6.3.dist-info/RECORD
