Metadata-Version: 2.3
Name: libactor
Version: 2.6.3
Summary: 
License: MIT
Author: Binh Vu
Author-email: bvu687@gmail.com
Requires-Python: >=3.11,<4.0
Classifier: License :: OSI Approved :: MIT License
Classifier: Programming Language :: Python :: 3
Classifier: Programming Language :: Python :: 3.11
Classifier: Programming Language :: Python :: 3.12
Classifier: Programming Language :: Python :: 3.13
Requires-Dist: hugedict (>=2.14.1,<3.0.0)
Requires-Dist: joblib (>=1.4.2,<2.0.0)
Requires-Dist: loguru (>=0.7.2,<0.8.0)
Requires-Dist: orjson (>=3.10.7,<4.0.0)
Requires-Dist: serde2 (>=1.9.0,<2.0.0)
